qrcode_img
