Metadata-Version: 2.1
Name: qrcode-img
Version: 1.0.8
Summary: Generation QR Code with IMG
Home-page: https://github.com/grand-roman/gen_qr_code_with_img
Author: Roman Andreev
Author-email: grand-roman@yandex.ru
Requires-Python: >=3.6
License-File: LICENSE
